{
  "hash": "c0e509e9",
  "configHash": "1d972885",
  "lockfileHash": "32378df8",
  "browserHash": "c87e90b5",
  "optimized": {
    "vue": {
      "src": "../../../../node_modules/vue/dist/vue.runtime.esm-bundler.js",
      "file": "vue.js",
      "fileHash": "19b0ec8d",
      "needsInterop": false
    },
    "vitepress > @vue/devtools-api": {
      "src": "../../../../node_modules/@vue/devtools-api/dist/index.js",
      "file": "vitepress___@vue_devtools-api.js",
      "fileHash": "530e850f",
      "needsInterop": false
    },
    "vitepress > @vueuse/core": {
      "src": "../../../../node_modules/@vueuse/core/index.mjs",
      "file": "vitepress___@vueuse_core.js",
      "fileHash": "6e734c36",
      "needsInterop": false
    },
    "@braintree/sanitize-url": {
      "src": "../../../../node_modules/@braintree/sanitize-url/dist/index.js",
      "file": "@braintree_sanitize-url.js",
      "fileHash": "b8fb460a",
      "needsInterop": true
    },
    "dayjs": {
      "src": "../../../../node_modules/dayjs/dayjs.min.js",
      "file": "dayjs.js",
      "fileHash": "c192a0b1",
      "needsInterop": true
    },
    "debug": {
      "src": "../../../../node_modules/debug/src/browser.js",
      "file": "debug.js",
      "fileHash": "fec8bd47",
      "needsInterop": true
    },
    "cytoscape-cose-bilkent": {
      "src": "../../../../node_modules/cytoscape-cose-bilkent/cytoscape-cose-bilkent.js",
      "file": "cytoscape-cose-bilkent.js",
      "fileHash": "dda641f0",
      "needsInterop": true
    },
    "cytoscape": {
      "src": "../../../../node_modules/cytoscape/dist/cytoscape.esm.mjs",
      "file": "cytoscape.js",
      "fileHash": "9c6ba578",
      "needsInterop": false
    },
    "vitepress-plugin-tabs/client": {
      "src": "../../../../node_modules/vitepress-plugin-tabs/src/client/index.ts",
      "file": "vitepress-plugin-tabs_client.js",
      "fileHash": "79f0798e",
      "needsInterop": false
    }
  },
  "chunks": {
    "chunk-TGLERUJR": {
      "file": "chunk-TGLERUJR.js"
    },
    "chunk-BUSYA2B4": {
      "file": "chunk-BUSYA2B4.js"
    }
  }
}